southern_company_api/__init__.py
southern_company_api/account.py
southern_company_api/company.py
southern_company_api/exceptions.py
southern_company_api/parser.py
southern_company_api/py.typed
southern_company_api-0.6.6.dist-info/LICENSE
southern_company_api-0.6.6.dist-info/METADATA
southern_company_api-0.6.6.dist-info/WHEEL
southern_company_api-0.6.6.dist-info/RECORD
