Metadata-Version: 2.3
Name: southern-company-api
Version: 0.6.6
Summary: Control Southern company websites with this api
License: MIT
Author: Luke
Author-email: conway220@gmail.com
Requires-Python: >=3.9,<4.0
Classifier: Development Status :: 2 - Pre-Alpha
Classifier: Intended Audience :: Developers
Classifier: License :: OSI Approved :: MIT License
Classifier: Natural Language :: English
Classifier: Operating System :: OS Independent
Classifier: Programming Language :: Python :: 3
Classifier: Programming Language :: Python :: 3.9
Classifier: Programming Language :: Python :: 3.10
Classifier: Programming Language :: Python :: 3.11
Classifier: Programming Language :: Python :: 3.12
Classifier: Programming Language :: Python :: 3.13
Classifier: Topic :: Software Development :: Libraries
Requires-Dist: PyJWT (>=2.0,<3.0)
Requires-Dist: aiohttp (>=3.8.1,<4.0.0)
Project-URL: Bug Tracker, https://github.com/Lash-L/southern-company-api/issues
Project-URL: Changelog, https://github.com/Lash-L/southern-company-api/blob/main/CHANGELOG.md
Project-URL: Repository, https://github.com/Lash-L/southern-company-api
